{
  "$id": "https://schema.hbp.eu/sand/0.1/core/annotation.schema.json",
  "$schema": "http://json-schema.org/draft-07/schema#",
  "description": "Definition of an annotation",
  "type": "object",
  "additionalProperties": false,
  "required": [
    "@type",
    "@id",
    "criteriaType",
    "laterality",
    "visualizedIn"
  ],
  "properties": {
    "@type": {
      "type": "string",
      "description": "Metadata node type (schema).",
      "const": "https://schema.ebrains.eu/sands/Annotation"
    },
    "@id": {
      "type": "string",
      "description": "Metadata node identifier (id).",
      "pattern": "sands/v0.1/core/annotation/([A-Za-z0-9_-]+).json"
    },
    "criteria": {
      "oneOf": [{
        "$ref": "https://raw.githubusercontent.com/HumanBrainProject/openMINDS/master/v1.0/definitions.json/PROTOCOL"
      }, {
        "$ref": "https://raw.githubusercontent.com/HumanBrainProject/openMINDS/master/v1.0/definitions.json/PROTOCOL_EXECUTION"
      }],    
      "description": "criteria"
    },
    "criteriaType": {
      "$ref": "https://raw.githubusercontent.com/HumanBrainProject/SANDS/master/v0.1/definitions.json#definitions/CONTROLLED_TERM",
      "description": "How was this annotation determined."
    },
    "definingTerm": {
      "$ref": "https://schema.hbp.eu/sands/core/anatomicalEntity.schema.json",
      "description": "Anatomical entity that provides the term for the here specified annotation."
    },
    "inspiredBy": {
      "$ref": "https://raw.githubusercontent.com/HumanBrainProject/SANDS/master/v0.1/definitions.json#definitions/IMAGE",
      "description": "Link to (source) image(s) that inspired the definition of this annotation."
    },
    "laterality": {
      "type": "array",
      "description": "The side of the body or bilateral organ that this annotation is defined in.",
      "items": {
        "$ref": "https://raw.githubusercontent.com/HumanBrainProject/SANDS/master/v0.1/definitions.json#definitions/CONTROLLED_TERM"
      },
      "maxItems": 2
    },
    "relatedAtlasTerm": {
      "$ref": "https://schema.hbp.eu/sands/core/anatomicalEntity.schema.json",
      "description": "Anatomical entity (term) of a brain atlas annotation to which the here specified annotation is related to."
    },
    "visualizedIn": {
      "$ref": "https://raw.githubusercontent.com/HumanBrainProject/SANDS/master/v0.1/definitions.json#definitions/VISUALIZATION_PARAMETERS",
      "description": "Link to visualization parameters of this annotation."
    }
  }
}
